README.md
setup.cfg
setup.py
extensible_cache/Cache.py
extensible_cache/MongoCache.py
extensible_cache/PandasCache.py
extensible_cache/__init__.py
extensible_cache.egg-info/PKG-INFO
extensible_cache.egg-info/SOURCES.txt
extensible_cache.egg-info/dependency_links.txt
extensible_cache.egg-info/not-zip-safe
extensible_cache.egg-info/requires.txt
extensible_cache.egg-info/top_level.txt