Metadata-Version: 2.1
Name: extensible-cache
Version: 1.0.1
Summary: Extensible Caching Framework for Python
Home-page: https://github.com/felixnext/PythonCache
Author: Felix Geilert
License: MIT License
Download-URL: https://github.com/felixnext/PythonCache/archive/refs/tags/v1.0.1.tar.gz
Keywords: cache;caching
Platform: UNKNOWN
